uf/__init__.py
uf/async_support.py
uf/base.py
uf/decorators.py
uf/field_interactions.py
uf/history.py
uf/organization.py
uf/pydantic_support.py
uf/renderers.py
uf/rjsf_config.py
uf/routes.py
uf/specs.py
uf/templates.py
uf/testing.py
uf/trans.py
uf-0.1.1.dist-info/METADATA
uf-0.1.1.dist-info/WHEEL
uf-0.1.1.dist-info/licenses/LICENSE
uf-0.1.1.dist-info/RECORD
