Metadata-Version: 2.4
Name: uf
Version: 0.1.1
Summary: UI Fast
Project-URL: Homepage, https://github.com/i2mint/uf
Project-URL: Repository, https://github.com/i2mint/uf
License: mit
License-File: LICENSE
Requires-Python: >=3.10
Requires-Dist: dol
Requires-Dist: i2
Requires-Dist: ju
Requires-Dist: meshed
Requires-Dist: qh
Provides-Extra: dev
Requires-Dist: pytest-cov>=4.0; extra == 'dev'
Requires-Dist: pytest>=7.0; extra == 'dev'
Requires-Dist: ruff>=0.1.0; extra == 'dev'
Provides-Extra: docs
Requires-Dist: sphinx-rtd-theme>=1.0; extra == 'docs'
Requires-Dist: sphinx>=6.0; extra == 'docs'
